model_server/__init__.py
model_server/about.py
model_server/core.py
model_server/runserver.py
model_server/server_pb2.py
model_server/server_pb2_grpc.py
model_server/apis/__init__.py
model_server/apis/predict_pb2.py
model_server/apis/predict_pb2_grpc.py
model_server/protos/__init__.py
model_server/protos/model_info_pb2.py
model_server/protos/model_info_pb2_grpc.py
model_server/protos/tensor_pb2.py
model_server/protos/tensor_pb2_grpc.py
model_server/utils/__init__.py
model_server/utils/model_info_utils.py
model_server/utils/prediction_utils.py
model_server/utils/tensor_utils.py
model_server-1.3.dist-info/licenses/LICENSE
model_server-1.3.dist-info/METADATA
model_server-1.3.dist-info/WHEEL
model_server-1.3.dist-info/top_level.txt
model_server-1.3.dist-info/RECORD
