Metadata-Version: 2.4
Name: model-server
Version: 1.3
Summary: Add your description here
Requires-Python: >=3.11
License-File: LICENSE
Requires-Dist: grpcio>=1.74.0
Requires-Dist: grpcio-tools>=1.74.0
Requires-Dist: numpy>=2.3.2
Dynamic: license-file
